[{"Year":2023,"Week":1,"Games":[{"Home":"Kansas City Chiefs","Away":"Detroit Lions","HomeScore":20,"AwayScore":21,"Date":"2023-09-07T00:00:00Z","Complete":true},{"Home":"Atlanta Falcons","Away":"Carolina Panthers","HomeScore":24,"AwayScore":10,"Date":"2023-09-10T00:00:00Z","Complete":true},{"Home":"Cleveland Browns","Away":"Cincinnati Bengals","HomeScore":24,"AwayScore":3,"Date":"2023-09-10T00:00:00Z","Complete":true},{"Home":"Indianapolis Colts","Away":"Jacksonville Jaguars","HomeScore":21,"AwayScore":31,"Date":"2023-09-10T00:00:00Z","Complete":true},{"Home":"Minnesota Vikings","Away":"Tampa Bay Buccaneers","HomeScore":17,"AwayScore":20,"Date":"2023-09-10T00:00:00Z","Complete":true},{"Home":"New Orleans Saints","Away":"Tennessee Titans","HomeScore":16,"AwayScore":15,"Date":"2023-09-10T00:00:00Z","Complete":true},{"Home":"Pittsburgh Steelers","Away":"San Francisco 49ers","HomeScore":7,"AwayScore":30,"Date":"2023-09-10T00:00:00Z","Complete":true},{"Home":"Baltimore Ravens","Away":"Houston Texans","HomeScore":25,"AwayScore":9,"Date":"2023-09-10T00:00:00Z","Complete":true},{"Home":"Washington Commanders","Away":"Arizona Cardinals","HomeScore":20,"AwayScore":16,"Date":"2023-09-10T00:00:00Z","Complete":true},{"Home":"Chicago Bears","Away":"Green Bay Packers","HomeScore":20,"AwayScore":38,"Date":"2023-09-10T00:00:00Z","Complete":true},{"Home":"Denver Broncos","Away":"Las Vegas Raiders","HomeScore":16,"AwayScore":17,"Date":"2023-09-10T00:00:00Z","Complete":true},{"Home":"New England Patriots","Away":"Philadelphia Eagles","HomeScore":20,"AwayScore":25,"Date":"2023-09-10T00:00:00Z","Complete":true},{"Home":"Los Angeles Chargers","Away":"Miami Dolphins","HomeScore":34,"AwayScore":36,"Date":"2023-09-10T00:00:00Z","Complete":true},{"Home":"Seattle Seahawks","Away":"Los Angeles Rams","HomeScore":13,"AwayScore":30,"Date":"2023-09-10T00:00:00Z","Complete":true},{"Home":"New York Giants","Away":"Dallas Cowboys","HomeScore":0,"AwayScore":40,"Date":"2023-09-10T00:00:00Z","Complete":true},{"Home":"New York Jets","Away":"Buffalo Bills","HomeScore":22,"AwayScore":16,"Date":"2023-09-11T00:00:00Z","Complete":true}]},{"Year":2023,"Week":2,"Games":[{"Home":"Philadelphia Eagles","Away":"Minnesota Vikings","HomeScore":34,"AwayScore":28,"Date":"2023-09-14T00:00:00Z","Complete":true},{"Home":"Atlanta Falcons","Away":"Green Bay Packers","HomeScore":25,"AwayScore":24,"Date":"2023-09-17T00:00:00Z","Complete":true},{"Home":"Buffalo Bills","Away":"Las Vegas Raiders","HomeScore":38,"AwayScore":10,"Date":"2023-09-17T00:00:00Z","Complete":true},{"Home":"Cincinnati Bengals","Away":"Baltimore Ravens","HomeScore":24,"AwayScore":27,"Date":"2023-09-17T00:00:00Z","Complete":true},{"Home":"Detroit Lions","Away":"Seattle Seahawks","HomeScore":31,"AwayScore":37,"Date":"2023-09-17T00:00:00Z","Complete":true},{"Home":"Houston Texans","Away":"Indianapolis Colts","HomeScore":20,"AwayScore":31,"Date":"2023-09-17T00:00:00Z","Complete":true},{"Home":"Jacksonville Jaguars","Away":"Kansas City Chiefs","HomeScore":9,"AwayScore":17,"Date":"2023-09-17T00:00:00Z","Complete":true},{"Home":"Tennessee Titans","Away":"Los Angeles Chargers","HomeScore":27,"AwayScore":24,"Date":"2023-09-17T00:00:00Z","Complete":true},{"Home":"Tampa Bay Buccaneers","Away":"Chicago Bears","HomeScore":27,"AwayScore":17,"Date":"2023-09-17T00:00:00Z","Complete":true},{"Home":"Arizona Cardinals","Away":"New York Giants","HomeScore":28,"AwayScore":31,"Date":"2023-09-17T00:00:00Z","Complete":true},{"Home":"Los Angeles Rams","Away":"San Francisco 49ers","HomeScore":23,"AwayScore":30,"Date":"2023-09-17T00:00:00Z","Complete":true},{"Home":"Dallas Cowboys","Away":"New York Jets","HomeScore":30,"AwayScore":10,"Date":"2023-09-17T00:00:00Z","Complete":true},{"Home":"Denver Broncos","Away":"Washington Commanders","HomeScore":33,"AwayScore":35,"Date":"2023-09-17T00:00:00Z","Complete":true},{"Home":"New England Patriots","Away":"Miami Dolphins","HomeScore":17,"AwayScore":24,"Date":"2023-09-17T00:00:00Z","Complete":true},{"Home":"Carolina Panthers","Away":"New Orleans Saints","HomeScore":17,"AwayScore":20,"Date":"2023-09-18T00:00:00Z","Complete":true},{"Home":"Pittsburgh Steelers","Away":"Cleveland Browns","HomeScore":26,"AwayScore":22,"Date":"2023-09-18T00:00:00Z","Complete":true}]},{"Year":2023,"Week":3,"Games":[{"Home":"San Francisco 49ers","Away":"New York Giants","HomeScore":30,"AwayScore":12,"Date":"2023-09-21T00:00:00Z","Complete":true},{"Home":"Cleveland Browns","Away":"Tennessee Titans","HomeScore":27,"AwayScore":3,"Date":"2023-09-24T00:00:00Z","Complete":true},{"Home":"Detroit Lions","Away":"Atlanta Falcons","HomeScore":20,"AwayScore":6,"Date":"2023-09-24T00:00:00Z","Complete":true},{"Home":"Green Bay Packers","Away":"New Orleans Saints","HomeScore":18,"AwayScore":17,"Date":"2023-09-24T00:00:00Z","Complete":true},{"Home":"Jacksonville Jaguars","Away":"Houston Texans","HomeScore":17,"AwayScore":37,"Date":"2023-09-24T00:00:00Z","Complete":true},{"Home":"Miami Dolphins","Away":"Denver Broncos","HomeScore":70,"AwayScore":20,"Date":"2023-09-24T00:00:00Z","Complete":true},{"Home":"Minnesota Vikings","Away":"Los Angeles Chargers","HomeScore":24,"AwayScore":28,"Date":"2023-09-24T00:00:00Z","Complete":true},{"Home":"New York Jets","Away":"New England Patriots","HomeScore":10,"AwayScore":15,"Date":"2023-09-24T00:00:00Z","Complete":true},{"Home":"Baltimore Ravens","Away":"Indianapolis Colts","HomeScore":19,"AwayScore":22,"Date":"2023-09-24T00:00:00Z","Complete":true},{"Home":"Washington Commanders","Away":"Buffalo Bills","HomeScore":3,"AwayScore":37,"Date":"2023-09-24T00:00:00Z","Complete":true},{"Home":"Seattle Seahawks","Away":"Carolina Panthers","HomeScore":37,"AwayScore":27,"Date":"2023-09-24T00:00:00Z","Complete":true},{"Home":"Arizona Cardinals","Away":"Dallas Cowboys","HomeScore":28,"AwayScore":16,"Date":"2023-09-24T00:00:00Z","Complete":true},{"Home":"Kansas City Chiefs","Away":"Chicago Bears","HomeScore":41,"AwayScore":10,"Date":"2023-09-24T00:00:00Z","Complete":true},{"Home":"Las Vegas Raiders","Away":"Pittsburgh Steelers","HomeScore":18,"AwayScore":23,"Date":"2023-09-24T00:00:00Z","Complete":true},{"Home":"Tampa Bay Buccaneers","Away":"Philadelphia Eagles","HomeScore":11,"AwayScore":25,"Date":"2023-09-25T00:00:00Z","Complete":true},{"Home":"Cincinnati Bengals","Away":"Los Angeles Rams","HomeScore":19,"AwayScore":16,"Date":"2023-09-25T00:00:00Z","Complete":true}]},{"Year":2023,"Week":4,"Games":[{"Home":"Green Bay Packers","Away":"Detroit Lions","HomeScore":20,"AwayScore":34,"Date":"2023-09-28T00:00:00Z","Complete":true},{"Home":"Jacksonville Jaguars","Away":"Atlanta Falcons","HomeScore":23,"AwayScore":7,"Date":"2023-10-01T00:00:00Z","Complete":true},{"Home":"Buffalo Bills","Away":"Miami Dolphins","HomeScore":48,"AwayScore":20,"Date":"2023-10-01T00:00:00Z","Complete":true},{"Home":"Carolina Panthers","Away":"Minnesota Vikings","HomeScore":13,"AwayScore":21,"Date":"2023-10-01T00:00:00Z","Complete":true},{"Home":"Chicago Bears","Away":"Denver Broncos","HomeScore":28,"AwayScore":31,"Date":"2023-10-01T00:00:00Z","Complete":true},{"Home":"Cleveland Browns","Away":"Baltimore Ravens","HomeScore":3,"AwayScore":28,"Date":"2023-10-01T00:00:00Z","Complete":true},{"Home":"Indianapolis Colts","Away":"Los Angeles Rams","HomeScore":23,"AwayScore":29,"Date":"2023-10-01T00:00:00Z","Complete":true},{"Home":"Houston Texans","Away":"Pittsburgh Steelers","HomeScore":30,"AwayScore":6,"Date":"2023-10-01T00:00:00Z","Complete":true},{"Home":"New Orleans Saints","Away":"Tampa Bay Buccaneers","HomeScore":9,"AwayScore":26,"Date":"2023-10-01T00:00:00Z","Complete":true},{"Home":"Tennessee Titans","Away":"Cincinnati Bengals","HomeScore":27,"AwayScore":3,"Date":"2023-10-01T00:00:00Z","Complete":true},{"Home":"Philadelphia Eagles","Away":"Washington Commanders","HomeScore":34,"AwayScore":31,"Date":"2023-10-01T00:00:00Z","Complete":true},{"Home":"Los Angeles Chargers","Away":"Las Vegas Raiders","HomeScore":24,"AwayScore":17,"Date":"2023-10-01T00:00:00Z","Complete":true},{"Home":"Dallas Cowboys","Away":"New England Patriots","HomeScore":38,"AwayScore":3,"Date":"2023-10-01T00:00:00Z","Complete":true},{"Home":"San Francisco 49ers","Away":"Arizona Cardinals","HomeScore":35,"AwayScore":16,"Date":"2023-10-01T00:00:00Z","Complete":true},{"Home":"New York Jets","Away":"Kansas City Chiefs","HomeScore":20,"AwayScore":23,"Date":"2023-10-01T00:00:00Z","Complete":true},{"Home":"New York Giants","Away":"Seattle Seahawks","HomeScore":3,"AwayScore":24,"Date":"2023-10-02T00:00:00Z","Complete":true}]},{"Year":2023,"Week":5,"Games":[{"Home":"Washington Commanders","Away":"Chicago Bears","HomeScore":20,"AwayScore":40,"Date":"2023-10-05T00:00:00Z","Complete":true},{"Home":"Buffalo Bills","Away":"Jacksonville Jaguars","HomeScore":20,"AwayScore":25,"Date":"2023-10-08T00:00:00Z","Complete":true},{"Home":"Atlanta Falcons","Away":"Houston Texans","HomeScore":21,"AwayScore":19,"Date":"2023-10-08T00:00:00Z","Complete":true},{"Home":"Indianapolis Colts","Away":"Tennessee Titans","HomeScore":23,"AwayScore":16,"Date":"2023-10-08T00:00:00Z","Complete":true},{"Home":"Detroit Lions","Away":"Carolina Panthers","HomeScore":42,"AwayScore":24,"Date":"2023-10-08T00:00:00Z","Complete":true},{"Home":"Miami Dolphins","Away":"New York Giants","HomeScore":31,"AwayScore":16,"Date":"2023-10-08T00:00:00Z","Complete":true},{"Home":"New England Patriots","Away":"New Orleans Saints","HomeScore":0,"AwayScore":34,"Date":"2023-10-08T00:00:00Z","Complete":true},{"Home":"Pittsburgh Steelers","Away":"Baltimore Ravens","HomeScore":17,"AwayScore":10,"Date":"2023-10-08T00:00:00Z","Complete":true},{"Home":"Arizona Cardinals","Away":"Cincinnati Bengals","HomeScore":20,"AwayScore":34,"Date":"2023-10-08T00:00:00Z","Complete":true},{"Home":"Los Angeles Rams","Away":"Philadelphia Eagles","HomeScore":14,"AwayScore":23,"Date":"2023-10-08T00:00:00Z","Complete":true},{"Home":"Denver Broncos","Away":"New York Jets","HomeScore":21,"AwayScore":31,"Date":"2023-10-08T00:00:00Z","Complete":true},{"Home":"Minnesota Vikings","Away":"Kansas City Chiefs","HomeScore":20,"AwayScore":27,"Date":"2023-10-08T00:00:00Z","Complete":true},{"Home":"San Francisco 49ers","Away":"Dallas Cowboys","HomeScore":42,"AwayScore":10,"Date":"2023-10-08T00:00:00Z","Complete":true},{"Home":"Las Vegas Raiders","Away":"Green Bay Packers","HomeScore":17,"AwayScore":13,"Date":"2023-10-09T00:00:00Z","Complete":true}]},{"Year":2023,"Week":6,"Games":[{"Home":"Kansas City Chiefs","Away":"Denver Broncos","HomeScore":19,"AwayScore":8,"Date":"2023-10-12T00:00:00Z","Complete":true},{"Home":"Tennessee Titans","Away":"Baltimore Ravens","HomeScore":16,"AwayScore":24,"Date":"2023-10-15T00:00:00Z","Complete":true},{"Home":"Atlanta Falcons","Away":"Washington Commanders","HomeScore":16,"AwayScore":24,"Date":"2023-10-15T00:00:00Z","Complete":true},{"Home":"Chicago Bears","Away":"Minnesota Vikings","HomeScore":13,"AwayScore":19,"Date":"2023-10-15T00:00:00Z","Complete":true},{"Home":"Cincinnati Bengals","Away":"Seattle Seahawks","HomeScore":17,"AwayScore":13,"Date":"2023-10-15T00:00:00Z","Complete":true},{"Home":"Cleveland Browns","Away":"San Francisco 49ers","HomeScore":19,"AwayScore":17,"Date":"2023-10-15T00:00:00Z","Complete":true},{"Home":"Houston Texans","Away":"New Orleans Saints","HomeScore":20,"AwayScore":13,"Date":"2023-10-15T00:00:00Z","Complete":true},{"Home":"Jacksonville Jaguars","Away":"Indianapolis Colts","HomeScore":37,"AwayScore":20,"Date":"2023-10-15T00:00:00Z","Complete":true},{"Home":"Miami Dolphins","Away":"Carolina Panthers","HomeScore":42,"AwayScore":21,"Date":"2023-10-15T00:00:00Z","Complete":true},{"Home":"Las Vegas Raiders","Away":"New England Patriots","HomeScore":21,"AwayScore":17,"Date":"2023-10-15T00:00:00Z","Complete":true},{"Home":"New York Jets","Away":"Philadelphia Eagles","HomeScore":20,"AwayScore":14,"Date":"2023-10-15T00:00:00Z","Complete":true},{"Home":"Los Angeles Rams","Away":"Arizona Cardinals","HomeScore":26,"AwayScore":9,"Date":"2023-10-15T00:00:00Z","Complete":true},{"Home":"Tampa Bay Buccaneers","Away":"Detroit Lions","HomeScore":6,"AwayScore":20,"Date":"2023-10-15T00:00:00Z","Complete":true},{"Home":"Buffalo Bills","Away":"New York Giants","HomeScore":14,"AwayScore":9,"Date":"2023-10-15T00:00:00Z","Complete":true},{"Home":"Los Angeles Chargers","Away":"Dallas Cowboys","HomeScore":17,"AwayScore":20,"Date":"2023-10-16T00:00:00Z","Complete":true}]},{"Year":2023,"Week":7,"Games":[{"Home":"New Orleans Saints","Away":"Jacksonville Jaguars","HomeScore":24,"AwayScore":31,"Date":"2023-10-19T00:00:00Z","Complete":true},{"Home":"Chicago Bears","Away":"Las Vegas Raiders","HomeScore":30,"AwayScore":12,"Date":"2023-10-22T00:00:00Z","Complete":true},{"Home":"Indianapolis Colts","Away":"Cleveland Browns","HomeScore":38,"AwayScore":39,"Date":"2023-10-22T00:00:00Z","Complete":true},{"Home":"New England Patriots","Away":"Buffalo Bills","HomeScore":29,"AwayScore":25,"Date":"2023-10-22T00:00:00Z","Complete":true},{"Home":"New York Giants","Away":"Washington Commanders","HomeScore":14,"AwayScore":7,"Date":"2023-10-22T00:00:00Z","Complete":true},{"Home":"Baltimore Ravens","Away":"Detroit Lions","HomeScore":38,"AwayScore":6,"Date":"2023-10-22T00:00:00Z","Complete":true},{"Home":"Tampa Bay Buccaneers","Away":"Atlanta Falcons","HomeScore":13,"AwayScore":16,"Date":"2023-10-22T00:00:00Z","Complete":true},{"Home":"Los Angeles Rams","Away":"Pittsburgh Steelers","HomeScore":17,"AwayScore":24,"Date":"2023-10-22T00:00:00Z","Complete":true},{"Home":"Seattle Seahawks","Away":"Arizona Cardinals","HomeScore":20,"AwayScore":10,"Date":"2023-10-22T00:00:00Z","Complete":true},{"Home":"Denver Broncos","Away":"Green Bay Packers","HomeScore":19,"AwayScore":17,"Date":"2023-10-22T00:00:00Z","Complete":true},{"Home":"Kansas City Chiefs","Away":"Los Angeles Chargers","HomeScore":31,"AwayScore":17,"Date":"2023-10-22T00:00:00Z","Complete":true},{"Home":"Philadelphia Eagles","Away":"Miami Dolphins","HomeScore":31,"AwayScore":17,"Date":"2023-10-22T00:00:00Z","Complete":true},{"Home":"Minnesota Vikings","Away":"San Francisco 49ers","HomeScore":22,"AwayScore":17,"Date":"2023-10-23T00:00:00Z","Complete":true}]},{"Year":2023,"Week":8,"Games":[{"Home":"Buffalo Bills","Away":"Tampa Bay Buccaneers","HomeScore":24,"AwayScore":18,"Date":"2023-10-26T00:00:00Z","Complete":true},{"Home":"Carolina Panthers","Away":"Houston Texans","HomeScore":15,"AwayScore":13,"Date":"2023-10-29T00:00:00Z","Complete":true},{"Home":"Indianapolis Colts","Away":"New Orleans Saints","HomeScore":27,"AwayScore":38,"Date":"2023-10-29T00:00:00Z","Complete":true},{"Home":"Dallas Cowboys","Away":"Los Angeles Rams","HomeScore":43,"AwayScore":20,"Date":"2023-10-29T00:00:00Z","Complete":true},{"Home":"Green Bay Packers","Away":"Minnesota Vikings","HomeScore":10,"AwayScore":24,"Date":"2023-10-29T00:00:00Z","Complete":true},{"Home":"Miami Dolphins","Away":"New England Patriots","HomeScore":31,"AwayScore":17,"Date":"2023-10-29T00:00:00Z","Complete":true},{"Home":"New York Giants","Away":"New York Jets","HomeScore":10,"AwayScore":13,"Date":"2023-10-29T00:00:00Z","Complete":true},{"Home":"Tennessee Titans","Away":"Atlanta Falcons","HomeScore":28,"AwayScore":23,"Date":"2023-10-29T00:00:00Z","Complete":true},{"Home":"Pittsburgh Steelers","Away":"Jacksonville Jaguars","HomeScore":10,"AwayScore":20,"Date":"2023-10-29T00:00:00Z","Complete":true},{"Home":"Washington Commanders","Away":"Philadelphia Eagles","HomeScore":31,"AwayScore":38,"Date":"2023-10-29T00:00:00Z","Complete":true},{"Home":"Seattle Seahawks","Away":"Cleveland Browns","HomeScore":24,"AwayScore":20,"Date":"2023-10-29T00:00:00Z","Complete":true},{"Home":"Arizona Cardinals","Away":"Baltimore Ravens","HomeScore":24,"AwayScore":31,"Date":"2023-10-29T00:00:00Z","Complete":true},{"Home":"Denver Broncos","Away":"Kansas City Chiefs","HomeScore":24,"AwayScore":9,"Date":"2023-10-29T00:00:00Z","Complete":true},{"Home":"San Francisco 49ers","Away":"Cincinnati Bengals","HomeScore":17,"AwayScore":31,"Date":"2023-10-29T00:00:00Z","Complete":true},{"Home":"Los Angeles Chargers","Away":"Chicago Bears","HomeScore":30,"AwayScore":13,"Date":"2023-10-29T00:00:00Z","Complete":true},{"Home":"Detroit Lions","Away":"Las Vegas Raiders","HomeScore":26,"AwayScore":14,"Date":"2023-10-30T00:00:00Z","Complete":true}]},{"Year":2023,"Week":9,"Games":[{"Home":"Pittsburgh Steelers","Away":"Tennessee Titans","HomeScore":20,"AwayScore":16,"Date":"2023-11-02T00:00:00Z","Complete":true},{"Home":"Kansas City Chiefs","Away":"Miami Dolphins","HomeScore":21,"AwayScore":14,"Date":"2023-11-05T00:00:00Z","Complete":true},{"Home":"Atlanta Falcons","Away":"Minnesota Vikings","HomeScore":28,"AwayScore":31,"Date":"2023-11-05T00:00:00Z","Complete":true},{"Home":"Cleveland Browns","Away":"Arizona Cardinals","HomeScore":27,"AwayScore":0,"Date":"2023-11-05T00:00:00Z","Complete":true},{"Home":"Green Bay Packers","Away":"Los Angeles Rams","HomeScore":20,"AwayScore":3,"Date":"2023-11-05T00:00:00Z","Complete":true},{"Home":"Houston Texans","Away":"Tampa Bay Buccaneers","HomeScore":39,"AwayScore":37,"Date":"2023-11-05T00:00:00Z","Complete":true},{"Home":"New Orleans Saints","Away":"Chicago Bears","HomeScore":24,"AwayScore":17,"Date":"2023-11-05T00:00:00Z","Complete":true},{"Home":"New England Patriots","Away":"Washington Commanders","HomeScore":17,"AwayScore":20,"Date":"2023-11-05T00:00:00Z","Complete":true},{"Home":"Baltimore Ravens","Away":"Seattle Seahawks","HomeScore":37,"AwayScore":3,"Date":"2023-11-05T00:00:00Z","Complete":true},{"Home":"Carolina Panthers","Away":"Indianapolis Colts","HomeScore":13,"AwayScore":27,"Date":"2023-11-05T00:00:00Z","Complete":true},{"Home":"Philadelphia Eagles","Away":"Dallas Cowboys","HomeScore":28,"AwayScore":23,"Date":"2023-11-05T00:00:00Z","Complete":true},{"Home":"Las Vegas Raiders","Away":"New York Giants","HomeScore":30,"AwayScore":6,"Date":"2023-11-05T00:00:00Z","Complete":true},{"Home":"Cincinnati Bengals","Away":"Buffalo Bills","HomeScore":24,"AwayScore":18,"Date":"2023-11-05T00:00:00Z","Complete":true},{"Home":"New York Jets","Away":"Los Angeles Chargers","HomeScore":6,"AwayScore":27,"Date":"2023-11-06T00:00:00Z","Complete":true}]},{"Year":2023,"Week":10,"Games":[{"Home":"Chicago Bears","Away":"Carolina Panthers","HomeScore":16,"AwayScore":13,"Date":"2023-11-09T00:00:00Z","Complete":true},{"Home":"New England Patriots","Away":"Indianapolis Colts","HomeScore":6,"AwayScore":10,"Date":"2023-11-12T00:00:00Z","Complete":true},{"Home":"Cincinnati Bengals","Away":"Houston Texans","HomeScore":27,"AwayScore":30,"Date":"2023-11-12T00:00:00Z","Complete":true},{"Home":"Jacksonville Jaguars","Away":"San Francisco 49ers","HomeScore":3,"AwayScore":34,"Date":"2023-11-12T00:00:00Z","Complete":true},{"Home":"Minnesota Vikings","Away":"New Orleans Saints","HomeScore":27,"AwayScore":19,"Date":"2023-11-12T00:00:00Z","Complete":true},{"Home":"Pittsburgh Steelers","Away":"Green Bay Packers","HomeScore":23,"AwayScore":19,"Date":"2023-11-12T00:00:00Z","Complete":true},{"Home":"Baltimore Ravens","Away":"Cleveland Browns","HomeScore":31,"AwayScore":33,"Date":"2023-11-12T00:00:00Z","Complete":true},{"Home":"Tampa Bay Buccaneers","Away":"Tennessee Titans","HomeScore":20,"AwayScore":6,"Date":"2023-11-12T00:00:00Z","Complete":true},{"Home":"Arizona Cardinals","Away":"Atlanta Falcons","HomeScore":25,"AwayScore":23,"Date":"2023-11-12T00:00:00Z","Complete":true},{"Home":"Los Angeles Chargers","Away":"Detroit Lions","HomeScore":38,"AwayScore":41,"Date":"2023-11-12T00:00:00Z","Complete":true},{"Home":"Dallas Cowboys","Away":"New York Giants","HomeScore":49,"AwayScore":17,"Date":"2023-11-12T00:00:00Z","Complete":true},{"Home":"Seattle Seahawks","Away":"Washington Commanders","HomeScore":29,"AwayScore":26,"Date":"2023-11-12T00:00:00Z","Complete":true},{"Home":"Las Vegas Raiders","Away":"New York Jets","HomeScore":16,"AwayScore":12,"Date":"2023-11-12T00:00:00Z","Complete":true},{"Home":"Buffalo Bills","Away":"Denver Broncos","HomeScore":22,"AwayScore":24,"Date":"2023-11-13T00:00:00Z","Complete":true}]},{"Year":2023,"Week":11,"Games":[{"Home":"Baltimore Ravens","Away":"Cincinnati Bengals","HomeScore":34,"AwayScore":20,"Date":"2023-11-16T00:00:00Z","Complete":true},{"Home":"Carolina Panthers","Away":"Dallas Cowboys","HomeScore":10,"AwayScore":33,"Date":"2023-11-19T00:00:00Z","Complete":true},{"Home":"Cleveland Browns","Away":"Pittsburgh Steelers","HomeScore":13,"AwayScore":10,"Date":"2023-11-19T00:00:00Z","Complete":true},{"Home":"Detroit Lions","Away":"Chicago Bears","HomeScore":31,"AwayScore":26,"Date":"2023-11-19T00:00:00Z","Complete":true},{"Home":"Green Bay Packers","Away":"Los Angeles Chargers","HomeScore":23,"AwayScore":20,"Date":"2023-11-19T00:00:00Z","Complete":true},{"Home":"Houston Texans","Away":"Arizona Cardinals","HomeScore":21,"AwayScore":16,"Date":"2023-11-19T00:00:00Z","Complete":true},{"Home":"Jacksonville Jaguars","Away":"Tennessee Titans","HomeScore":34,"AwayScore":14,"Date":"2023-11-19T00:00:00Z","Complete":true},{"Home":"Miami Dolphins","Away":"Las Vegas Raiders","HomeScore":20,"AwayScore":13,"Date":"2023-11-19T00:00:00Z","Complete":true},{"Home":"Washington Commanders","Away":"New York Giants","HomeScore":19,"AwayScore":31,"Date":"2023-11-19T00:00:00Z","Complete":true},{"Home":"San Francisco 49ers","Away":"Tampa Bay Buccaneers","HomeScore":27,"AwayScore":14,"Date":"2023-11-19T00:00:00Z","Complete":true},{"Home":"Buffalo Bills","Away":"New York Jets","HomeScore":32,"AwayScore":6,"Date":"2023-11-19T00:00:00Z","Complete":true},{"Home":"Los Angeles Rams","Away":"Seattle Seahawks","HomeScore":17,"AwayScore":16,"Date":"2023-11-19T00:00:00Z","Complete":true},{"Home":"Denver Broncos","Away":"Minnesota Vikings","HomeScore":21,"AwayScore":20,"Date":"2023-11-19T00:00:00Z","Complete":true},{"Home":"Kansas City Chiefs","Away":"Philadelphia Eagles","HomeScore":17,"AwayScore":21,"Date":"2023-11-20T00:00:00Z","Complete":true}]},{"Year":2023,"Week":12,"Games":[{"Home":"Detroit Lions","Away":"Green Bay Packers","HomeScore":22,"AwayScore":29,"Date":"2023-11-23T00:00:00Z","Complete":true},{"Home":"Dallas Cowboys","Away":"Washington Commanders","HomeScore":45,"AwayScore":10,"Date":"2023-11-23T00:00:00Z","Complete":true},{"Home":"Seattle Seahawks","Away":"San Francisco 49ers","HomeScore":13,"AwayScore":31,"Date":"2023-11-23T00:00:00Z","Complete":true},{"Home":"New York Jets","Away":"Miami Dolphins","HomeScore":13,"AwayScore":34,"Date":"2023-11-24T00:00:00Z","Complete":true},{"Home":"Atlanta Falcons","Away":"New Orleans Saints","HomeScore":24,"AwayScore":15,"Date":"2023-11-26T00:00:00Z","Complete":true},{"Home":"Cincinnati Bengals","Away":"Pittsburgh Steelers","HomeScore":10,"AwayScore":16,"Date":"2023-11-26T00:00:00Z","Complete":true},{"Home":"Indianapolis Colts","Away":"Tampa Bay Buccaneers","HomeScore":27,"AwayScore":20,"Date":"2023-11-26T00:00:00Z","Complete":true},{"Home":"Houston Texans","Away":"Jacksonville Jaguars","HomeScore":21,"AwayScore":24,"Date":"2023-11-26T00:00:00Z","Complete":true},{"Home":"New York Giants","Away":"New England Patriots","HomeScore":10,"AwayScore":7,"Date":"2023-11-26T00:00:00Z","Complete":true},{"Home":"Tennessee Titans","Away":"Carolina Panthers","HomeScore":17,"AwayScore":10,"Date":"2023-11-26T00:00:00Z","Complete":true},{"Home":"Arizona Cardinals","Away":"Los Angeles Rams","HomeScore":14,"AwayScore":37,"Date":"2023-11-26T00:00:00Z","Complete":true},{"Home":"Denver Broncos","Away":"Cleveland Browns","HomeScore":29,"AwayScore":12,"Date":"2023-11-26T00:00:00Z","Complete":true},{"Home":"Philadelphia Eagles","Away":"Buffalo Bills","HomeScore":37,"AwayScore":34,"Date":"2023-11-26T00:00:00Z","Complete":true},{"Home":"Las Vegas Raiders","Away":"Kansas City Chiefs","HomeScore":17,"AwayScore":31,"Date":"2023-11-26T00:00:00Z","Complete":true},{"Home":"Los Angeles Chargers","Away":"Baltimore Ravens","HomeScore":10,"AwayScore":20,"Date":"2023-11-26T00:00:00Z","Complete":true},{"Home":"Minnesota Vikings","Away":"Chicago Bears","HomeScore":10,"AwayScore":12,"Date":"2023-11-27T00:00:00Z","Complete":true}]},{"Year":2023,"Week":13,"Games":[{"Home":"Dallas Cowboys","Away":"Seattle Seahawks","HomeScore":41,"AwayScore":35,"Date":"2023-11-30T00:00:00Z","Complete":true},{"Home":"Houston Texans","Away":"Denver Broncos","HomeScore":22,"AwayScore":17,"Date":"2023-12-03T00:00:00Z","Complete":true},{"Home":"New Orleans Saints","Away":"Detroit Lions","HomeScore":28,"AwayScore":33,"Date":"2023-12-03T00:00:00Z","Complete":true},{"Home":"New England Patriots","Away":"Los Angeles Chargers","HomeScore":0,"AwayScore":6,"Date":"2023-12-03T00:00:00Z","Complete":true},{"Home":"New York Jets","Away":"Atlanta Falcons","HomeScore":8,"AwayScore":13,"Date":"2023-12-03T00:00:00Z","Complete":true},{"Home":"Tennessee Titans","Away":"Indianapolis Colts","HomeScore":28,"AwayScore":31,"Date":"2023-12-03T00:00:00Z","Complete":true},{"Home":"Pittsburgh Steelers","Away":"Arizona Cardinals","HomeScore":10,"AwayScore":24,"Date":"2023-12-03T00:00:00Z","Complete":true},{"Home":"Washington Commanders","Away":"Miami Dolphins","HomeScore":15,"AwayScore":45,"Date":"2023-12-03T00:00:00Z","Complete":true},{"Home":"Tampa Bay Buccaneers","Away":"Carolina Panthers","HomeScore":21,"AwayScore":18,"Date":"2023-12-03T00:00:00Z","Complete":true},{"Home":"Philadelphia Eagles","Away":"San Francisco 49ers","HomeScore":19,"AwayScore":42,"Date":"2023-12-03T00:00:00Z","Complete":true},{"Home":"Los Angeles Rams","Away":"Cleveland Browns","HomeScore":36,"AwayScore":19,"Date":"2023-12-03T00:00:00Z","Complete":true},{"Home":"Green Bay Packers","Away":"Kansas City Chiefs","HomeScore":27,"AwayScore":19,"Date":"2023-12-03T00:00:00Z","Complete":true},{"Home":"Jacksonville Jaguars","Away":"Cincinnati Bengals","HomeScore":31,"AwayScore":34,"Date":"2023-12-04T00:00:00Z","Complete":true}]},{"Year":2023,"Week":14,"Games":null},{"Year":2023,"Week":15,"Games":null},{"Year":2023,"Week":16,"Games":null},{"Year":2023,"Week":17,"Games":null},{"Year":2023,"Week":18,"Games":null}]